cloe_synthetic_data_generator/__init__.py
cloe_synthetic_data_generator/cli.py
cloe_synthetic_data_generator/config.py
cloe_synthetic_data_generator/config_loader.py
cloe_synthetic_data_generator/py.typed
cloe_synthetic_data_generator/spark_utils.py
cloe_synthetic_data_generator/discovery/__init__.py
cloe_synthetic_data_generator/discovery/config_generator.py
cloe_synthetic_data_generator/discovery/table_discovery.py
cloe_synthetic_data_generator/discovery/yaml_writer.py
cloe_synthetic_data_generator/generate/__init__.py
cloe_synthetic_data_generator/generate/data_generator.py
cloe_synthetic_data_generator/generate/data_processor.py
cloe_synthetic_data_generator/generate/unity_catalog_writer.py
cloe_synthetic_data_generator-0.2.1.dist-info/METADATA
cloe_synthetic_data_generator-0.2.1.dist-info/WHEEL
cloe_synthetic_data_generator-0.2.1.dist-info/entry_points.txt
cloe_synthetic_data_generator-0.2.1.dist-info/RECORD
