Metadata-Version: 2.4
Name: cloe-synthetic-data-generator
Version: 0.2.1
Summary: A new cool package.
Author-email: initions <ICSMC_EXT_PYPIORG@accenture.com>
License: MIT
Classifier: Development Status :: 5 - Production/Stable
Classifier: Environment :: Console
Classifier: Intended Audience :: Developers
Classifier: License :: OSI Approved :: MIT License
Classifier: Operating System :: OS Independent
Classifier: Programming Language :: Python :: 3
Classifier: Topic :: Database
Requires-Python: ~=3.12.3
Requires-Dist: databricks-connect~=16.4.0
Requires-Dist: faker~=37.4.2
Requires-Dist: pydantic-settings~=2.8.0
Requires-Dist: pydantic~=2.10.3
Requires-Dist: pyyaml~=6.0.2
Requires-Dist: rich~=13.9.4
Requires-Dist: typer~=0.15.1
